hpmoc/__init__.py
hpmoc/abstract.py
hpmoc/arraysetops.py
hpmoc/healpy.py
hpmoc/healpy_utils.py
hpmoc/partial.py
hpmoc/plot.py
hpmoc/plotters.py
hpmoc/points.py
hpmoc/psf.py
hpmoc/utils.py
hpmoc/io/__init__.py
hpmoc/io/abstract.py
hpmoc/io/astroquery.py
hpmoc/io/fits.py
hpmoc/io/gracedb.py
hpmoc/io/ligo.py
hpmoc-1.0.0.dist-info/LICENSE
hpmoc-1.0.0.dist-info/WHEEL
hpmoc-1.0.0.dist-info/METADATA
hpmoc-1.0.0.dist-info/RECORD
